SparseMatrixRecommender/CrossTabulate.py
SparseMatrixRecommender/DataLoaders.py
SparseMatrixRecommender/DocumentTermWeightFunctions.py
SparseMatrixRecommender/SparseMatrixRecommender.py
SparseMatrixRecommender/__init__.py
SparseMatrixRecommender/resources/dfMintBubblesTransactions.csv
SparseMatrixRecommender/resources/dfMushroom.csv.gz
SparseMatrixRecommender/resources/dfTitanic.csv
sparsematrixrecommender-0.1.11.dist-info/licenses/LICENSE
sparsematrixrecommender-0.1.11.dist-info/METADATA
sparsematrixrecommender-0.1.11.dist-info/WHEEL
sparsematrixrecommender-0.1.11.dist-info/top_level.txt
sparsematrixrecommender-0.1.11.dist-info/RECORD
