Metadata-Version: 2.4
Name: SparseMatrixRecommender
Version: 0.1.11
Summary: Sparse Matrix Recommender package based on SSparseMatrix objects.
Home-page: https://github.com/antononcube/Python-packages/tree/main/SparseMatrixRecommender
Author: Anton Antonov
Author-email: antononcube@posteo.net
Keywords: sparse,matrix,recommender,sparse matrix recommender,linear algebra,linear,algebra,recommendations
Classifier: Programming Language :: Python :: 3
Classifier: License :: OSI Approved :: GNU General Public License v3 (GPLv3)
Classifier: Operating System :: OS Independent
Requires-Python: >=3.7
License-File: LICENSE
Requires-Dist: numpy
Requires-Dist: scipy
Requires-Dist: SSparseMatrix
Requires-Dist: pandas
Dynamic: author
Dynamic: author-email
Dynamic: classifier
Dynamic: description
Dynamic: description-content-type
Dynamic: home-page
Dynamic: keywords
Dynamic: license-file
Dynamic: requires-dist
Dynamic: requires-python
Dynamic: summary
